test/__init__.py
test/run_test.py
torchwisdom/__init__.py
torchwisdom/audio/__init__.py
torchwisdom/core/__init__.py
torchwisdom/core/envi.py
torchwisdom/core/predictor.py
torchwisdom/core/progress.py
torchwisdom/core/callback/__init__.py
torchwisdom/core/callback/core.py
torchwisdom/core/callback/logger.py
torchwisdom/core/callback/metrics.py
torchwisdom/core/callback/model.py
torchwisdom/core/callback/optimizer.py
torchwisdom/core/callback/statemgr.py
torchwisdom/core/metrics/__init__.py
torchwisdom/core/metrics/functional.py
torchwisdom/core/metrics/metrics.py
torchwisdom/core/nn/__init__.py
torchwisdom/core/nn/functional.py
torchwisdom/core/nn/layers.py
torchwisdom/core/nn/loss.py
torchwisdom/core/optim/__init__.py
torchwisdom/core/optim/wrapper.py
torchwisdom/core/statemgr/__init__.py
torchwisdom/core/statemgr/state.py
torchwisdom/core/trainer/__init__.py
torchwisdom/core/trainer/base.py
torchwisdom/core/trainer/helpers.py
torchwisdom/core/trainer/semi_supervise.py
torchwisdom/core/trainer/supervise.py
torchwisdom/core/utils/__init__.py
torchwisdom/core/utils/utils.py
torchwisdom/core/utils/data/__init__.py
torchwisdom/core/utils/data/collector.py
torchwisdom/core/utils/data/split.py
torchwisdom/tabular/__init__.py
torchwisdom/tabular/collector.py
torchwisdom/tabular/datasets.py
torchwisdom/tabular/models.py
torchwisdom/tabular/predictor.py
torchwisdom/tabular/trainer.py
torchwisdom/tabular/transforms.py
torchwisdom/tabular/utils.py
torchwisdom/text/__init__.py
torchwisdom/vision/__init__.py
torchwisdom/vision/predictor.py
torchwisdom/vision/utils.py
torchwisdom/vision/viz.py
torchwisdom/vision/data/__init__.py
torchwisdom/vision/data/collector.py
torchwisdom/vision/data/datasets.py
torchwisdom/vision/data/helpers.py
torchwisdom/vision/data/utils.py
torchwisdom/vision/models/__init__.py
torchwisdom/vision/models/alexnet.py
torchwisdom/vision/models/darknet.py
torchwisdom/vision/models/mobilenet.py
torchwisdom/vision/models/resnet.py
torchwisdom-0.0.2.dist-info/LICENSE
torchwisdom-0.0.2.dist-info/METADATA
torchwisdom-0.0.2.dist-info/WHEEL
torchwisdom-0.0.2.dist-info/top_level.txt
torchwisdom-0.0.2.dist-info/RECORD
