Metadata-Version: 2.1
Name: torchwisdom
Version: 0.0.2
Summary: A High Level API for PyTorch
Home-page: https://github.com/nunenuh/torchwisdom
Author: Lalu Erfandi Maula Yusnu
Author-email: nunenuh@gmail.com
License: UNKNOWN
Project-URL: Bug Reports, https://github.com/nunenuh/torchwisdom/issues
Project-URL: Source, https://github.com/nunenuh/torchwisdom/
Keywords: pytorch deep learning machine learning
Platform: UNKNOWN
Classifier: Development Status :: 3 - Alpha
Classifier: Intended Audience :: Developers
Classifier: Topic :: Software Development
Classifier: License :: OSI Approved :: MIT License
Classifier: Programming Language :: Python :: 3.5
Classifier: Programming Language :: Python :: 3.6
Requires-Python: >=3.5, <=3.6
Requires-Dist: torch
Requires-Dist: torchvision
Provides-Extra: dev
Requires-Dist: check-manifest ; extra == 'dev'
Provides-Extra: test
Requires-Dist: coverage ; extra == 'test'
